fillblank/__init__.py
fillblank/fillblank.py
fillblank-1.0.1.dist-info/LICENSE
fillblank-1.0.1.dist-info/METADATA
fillblank-1.0.1.dist-info/WHEEL
fillblank-1.0.1.dist-info/top_level.txt
fillblank-1.0.1.dist-info/RECORD
