Metadata-Version: 2.1
Name: fillblank
Version: 1.0.1
Summary: Fill the blank using transformers
Home-page: https://github.com/sagorbrur/fillblank
Author: Sagor Sarker
Author-email: sagorhem3532@gmail.com
License: MIT
Platform: UNKNOWN
Classifier: Programming Language :: Python :: 3
Classifier: License :: OSI Approved :: MIT License
Classifier: Operating System :: OS Independent
Requires-Python: >=3.5
Requires-Dist: transformers
Requires-Dist: nltk
